parallelsdk/__init__.py
parallelsdk/client.py
parallelsdk/connector.py
parallelsdk/connector_factory.py
parallelsdk/connector_toolbox.py
parallelsdk/frontend_client_runner.py
parallelsdk/main.py
parallelsdk/parallel_model.py
parallelsdk/cp_toolbox/__init__.py
parallelsdk/cp_toolbox/cp_problem.py
parallelsdk/cp_toolbox/cp_problem_proxy.py
parallelsdk/cp_toolbox/cp_sat_problem.py
parallelsdk/cp_toolbox/cp_toolbox.py
parallelsdk/cp_toolbox/optimizer_cp_model.py
parallelsdk/cp_toolbox/CPModels/__init__.py
parallelsdk/cp_toolbox/CPModels/constraint.py
parallelsdk/cp_toolbox/CPModels/variable.py
parallelsdk/data_toolbox/__init__.py
parallelsdk/data_toolbox/data_port_tools.py
parallelsdk/data_toolbox/data_toolbox.py
parallelsdk/data_toolbox/optimizer_data_port_tools.py
parallelsdk/data_toolbox/python_function_tool.py
parallelsdk/deployment/__init__.py
parallelsdk/deployment/deployment_model.py
parallelsdk/evolutionary_toolbox/__init__.py
parallelsdk/evolutionary_toolbox/evolutionary_problem.py
parallelsdk/evolutionary_toolbox/evolutionary_toolbox.py
parallelsdk/evolutionary_toolbox/genetic_problem.py
parallelsdk/evolutionary_toolbox/optimizer_evolutionary_model.py
parallelsdk/evolutionary_toolbox/EvolutionaryModels/Chromosome.py
parallelsdk/evolutionary_toolbox/EvolutionaryModels/GeneticEnvironment.py
parallelsdk/evolutionary_toolbox/EvolutionaryModels/__init__.py
parallelsdk/mp_toolbox/__init__.py
parallelsdk/mp_toolbox/constraints.py
parallelsdk/mp_toolbox/mp_model.py
parallelsdk/mp_toolbox/mp_toolbox.py
parallelsdk/mp_toolbox/objects.py
parallelsdk/mp_toolbox/optimizer_mp_model.py
parallelsdk/mp_toolbox/variables.py
parallelsdk/parallel_client_websocket/__init__.py
parallelsdk/parallel_client_websocket/_abnf.py
parallelsdk/parallel_client_websocket/_app.py
parallelsdk/parallel_client_websocket/_cookiejar.py
parallelsdk/parallel_client_websocket/_core.py
parallelsdk/parallel_client_websocket/_exceptions.py
parallelsdk-0.5.9.6.dist-info/DESCRIPTION.rst
parallelsdk-0.5.9.6.dist-info/METADATA
parallelsdk-0.5.9.6.dist-info/RECORD
parallelsdk-0.5.9.6.dist-info/WHEEL
parallelsdk-0.5.9.6.dist-info/metadata.json
parallelsdk-0.5.9.6.dist-info/top_level.txt
