Metadata-Version: 2.0
Name: parallelsdk
Version: 0.5.9.6
Summary: Parallel AI Frontend Python SDK
Home-page: UNKNOWN
Author: Austin Garrett
Author-email: agarrett777@gmail.com
License: UNKNOWN
Platform: UNKNOWN
Requires-Dist: numpy
Requires-Dist: sympy
Requires-Dist: protobuf
Requires-Dist: ipykernel
Requires-Dist: pyzmq
Requires-Dist: tornado
Requires-Dist: sklearn
Requires-Dist: ortools
